{"secret_tunnel": {"url": "https://youtu.be/7o4EI_-5reA", "ts": 65.5, "clip_duration": 7.2, "name": "Secret Tunnel", "volume": 1}, "dumb_ways_to_die": {"url": "https://youtu.be/IJNR2EpS0jw", "ts": 18.5, "clip_duration": 7, "name": "Dumb Ways to Die", "volume": 0.4}, "yall_aint_sleeping": {"url": "https://youtu.be/110l4ynyhII", "ts": 0, "clip_duration": 4, "name": "Y'all Ain't Get No Sleep", "volume": 0.9}, "think_you_the_shit": {"url": "https://youtu.be/2jjXeFZSQy0", "ts": 16, "clip_duration": 6, "name": "Think You the Shit?", "volume": 0.4}, "huh_cat": {"url": "https://youtu.be/xVWeRnStdSA", "ts": 1, "clip_duration": 3, "name": "Huh?", "volume": 0.5}, "carmelldansen": {"url": "https://youtu.be/zvq9r6R6QAY", "ts": 53, "clip_duration": 10, "name": "Carmelldansen", "volume": 0.3}, "cat_gag": {"url": "https://youtu.be/aHXx15ahNtw", "ts": 4, "clip_duration": 2, "name": "Cat Gag", "volume": 1}, "waterfalls": {"url": "https://youtu.be/8WEtxJ4-sh4", "ts": 117, "clip_duration": 7, "name": "Waterfalls", "volume": 0.7}, "skyrim_battle_theme": {"url": "https://youtu.be/YVTR8lTnnx8", "ts": 0, "clip_duration": 10, "name": "Time to Die", "volume": 0.8}, "yes_roundabout": {"url": "https://youtu.be/7uBqNgxAuBA", "ts": 40, "clip_duration": 8, "name": "Roll Initiative! (TBD)", "volume": 0.8}, "god_and_anime": {"url": "https://youtu.be/9vcYBmeBliI", "ts": 2.0, "clip_duration": 5.0, "name": "God and Anime", "volume": 0.8}}